xaal/__init__.py
xaal/ipx800/__init__.py
xaal/ipx800/__main__.py
xaal/ipx800/devices.py
xaal/ipx800/gw.py
xaal_ipx800-0.2.2.dist-info/METADATA
xaal_ipx800-0.2.2.dist-info/WHEEL
xaal_ipx800-0.2.2.dist-info/top_level.txt
xaal_ipx800-0.2.2.dist-info/RECORD
